aws_sam_utils/__init__.py
aws_sam_utils/cli.py
aws_sam_utils/dynamodb_schema/create_dynamodb_cf_template.py
aws_sam_utils/dynamodb_schema/create_dynamodb_local_json.py
aws_sam_utils/dynamodb_schema/schema.yaml
aws_sam_utils/dynamodb_schema/shared.py
aws_sam_utils/project_devops_stack/WorkDir.py
aws_sam_utils/project_devops_stack/__init__.py
aws_sam_utils/project_devops_stack/entry.py
aws_sam_utils/project_devops_stack/samconfig.toml
aws_sam_utils/project_devops_stack/cmd/SamTearDownWorkDir.py
aws_sam_utils/project_devops_stack/cmd/SamSetupWorkDir/__init__.py
aws_sam_utils/project_devops_stack/cmd/SamSetupWorkDir/template/__init__.py
aws_sam_utils/project_devops_stack/cmd/SamSetupWorkDir/template/index.yaml
aws_sam_utils/project_devops_stack/cmd/SamSetupWorkDir/template/include/__init__.py
aws_sam_utils/project_devops_stack/cmd/SamSetupWorkDir/template/include/codebuild-integrate.yaml
aws_sam_utils/project_devops_stack/cmd/SamSetupWorkDir/template/include/codecommit-repo.yaml
aws_sam_utils/project_devops_stack/cmd/SamSetupWorkDir/template/include/pull_request_build_status_func.py
aws_sam_utils/project_devops_stack/cmd/SamSetupWorkDir/template/include/s3_file_func.py
aws_sam_utils/runner/TemplateRunner.py
aws_sam_utils/runner/__init__.py
aws_sam_utils/runner/samconfig.toml
aws_sam_utils/runner/DevOpsRunner/__init__.py
aws_sam_utils/runner/DevOpsRunner/template.yaml
aws_sam_utils/runner/HttpWebsiteRunner/__init__.py
aws_sam_utils/runner/HttpWebsiteRunner/template.yaml
aws_sam_utils/runner/HttpsNoLogWebsiteRunner/__init__.py
aws_sam_utils/runner/HttpsNoLogWebsiteRunner/acm-certificate.yaml
aws_sam_utils/runner/HttpsNoLogWebsiteRunner/cloudfront-site.yaml
aws_sam_utils/runner/HttpsNoLogWebsiteRunner/s3-bucket.yaml
aws_sam_utils/runner/HttpsNoLogWebsiteRunner/template.yaml
aws_sam_utils/runner/HttpsWebsiteRunner/__init__.py
aws_sam_utils/runner/HttpsWebsiteRunner/acm-certificate.yaml
aws_sam_utils/runner/HttpsWebsiteRunner/cloudfront-site.yaml
aws_sam_utils-1.0.1.dist-info/LICENSE
aws_sam_utils-1.0.1.dist-info/METADATA
aws_sam_utils-1.0.1.dist-info/WHEEL
aws_sam_utils-1.0.1.dist-info/entry_points.txt
aws_sam_utils-1.0.1.dist-info/top_level.txt
aws_sam_utils-1.0.1.dist-info/RECORD
